LICENSE
MANIFEST.in
README.md
setup.py
Topsis_Gaurav_101803221.egg-info/PKG-INFO
Topsis_Gaurav_101803221.egg-info/SOURCES.txt
Topsis_Gaurav_101803221.egg-info/dependency_links.txt
Topsis_Gaurav_101803221.egg-info/entry_points.txt
Topsis_Gaurav_101803221.egg-info/requires.txt
Topsis_Gaurav_101803221.egg-info/top_level.txt
Topsis_python/101803221_Gaurav.py