Metadata-Version: 2.1
Name: Topsis-Gaurav-101803221
Version: 0.0.7
Summary: A Python package implementing TOPSIS technique.
Home-page: UNKNOWN
Author: Gaurav
Author-email: bhandalgaurav1999@gmail.com
License: MIT
Platform: UNKNOWN
Classifier: License :: OSI Approved :: MIT License
Classifier: Programming Language :: Python :: 3
Classifier: Programming Language :: Python :: 3.7
